{"namespace":"RoastMyRideDesignSystem_896616","components":[{"name":"CastPicker","sourcePath":"components/cast/CastPicker.jsx"},{"name":"Roaster","sourcePath":"components/cast/Roaster.jsx"},{"name":"Badge","sourcePath":"components/core/Badge.jsx"},{"name":"Button","sourcePath":"components/core/Button.jsx"},{"name":"Card","sourcePath":"components/core/Card.jsx"},{"name":"Chip","sourcePath":"components/core/Chip.jsx"},{"name":"Input","sourcePath":"components/core/Input.jsx"},{"name":"Confetti","sourcePath":"components/feedback/Confetti.jsx"},{"name":"Sheet","sourcePath":"components/feedback/Sheet.jsx"},{"name":"Toast","sourcePath":"components/feedback/Toast.jsx"},{"name":"Mascot","sourcePath":"components/mascot/Mascot.jsx"},{"name":"Callie","sourcePath":"components/mascot/Mascot.jsx"},{"name":"MascotHost","sourcePath":"components/mascot/Mascot.jsx"},{"name":"CallieHost","sourcePath":"components/mascot/Mascot.jsx"},{"name":"CreditTile","sourcePath":"components/share/CreditTile.jsx"},{"name":"ShareCard","sourcePath":"components/share/ShareCard.jsx"}],"startingPoints":[{"name":"roastmyride-app","path":"apps/roastmyride-app/index.html","previewPath":"apps/roastmyride-app/index.html","kind":"screen","section":"App","subtitle":"Full iOS app flow (9 screens)","viewport":"430x880"},{"name":"CastPicker","path":"components/cast/CastPicker.jsx","previewPath":"components/cast/cast.card.html","kind":"component","section":"Brand","subtitle":"The cast / character picker","viewport":"430x640"},{"name":"Roaster","path":"components/cast/Roaster.jsx","previewPath":"components/cast/cast.card.html","kind":"component","section":"Brand","subtitle":"The 8-roaster voice cast","viewport":"700x320"},{"name":"call-companion","path":"apps/call-companion/index.html","previewPath":"apps/call-companion/index.html","kind":"screen","section":"Call Companion","subtitle":"Incoming-call hero screen","viewport":"430x880"},{"name":"Button","path":"components/core/Button.jsx","previewPath":"components/core/core.card.html","kind":"component","section":"Core","subtitle":"Inflatable CTA with squish press","viewport":"700x160"},{"name":"Card","path":"components/core/Card.jsx","previewPath":"components/core/core.card.html","kind":"component","section":"Core","subtitle":"Glossy card with optional corner sticker","viewport":"700x240"},{"name":"Sheet","path":"components/feedback/Sheet.jsx","previewPath":"components/feedback/feedback.card.html","kind":"component","section":"Feedback","subtitle":"Bouncy bottom sheet with mascot header","viewport":"430x520"},{"name":"roastmyride-web","path":"apps/roastmyride-web/index.html","previewPath":"apps/roastmyride-web/index.html","kind":"screen","section":"Website","subtitle":"Single-CTA viral landing page","viewport":"1280x900"}],"cards":[{"path":"apps/roastmyride-app/index.html","group":"App","viewport":"430x880","subtitle":"Interactive 9-screen flow: onboarding → upload → reveal → share","name":"RoastMyRide iOS app"},{"path":"guidelines/brand-logo.card.html","group":"Brand","viewport":"700x180","subtitle":"Glossy flame mark + chunky display wordmark","name":"Logo lockup"},{"path":"guidelines/brand-motion.card.html","group":"Brand","viewport":"700x220","subtitle":"Press squishes 0.94; entrances spring; confetti is decoration-only","name":"Motion note — squish, bounce, confetti + reduce-motion"},{"path":"guidelines/brand-principle.card.html","group":"Brand","viewport":"700x200","subtitle":"Chaos lives only in the decoration layer; bones stay AA-legible","name":"The one rule — maximalist skin, clean bones"},{"path":"apps/call-companion/index.html","group":"Call Companion","viewport":"430x880","subtitle":"Second app, same core, cool accent — a character calls; Callie reacts","name":"Call Companion — incoming call"},{"path":"guidelines/color-accent.card.html","group":"Colors","viewport":"700x150","subtitle":"Each app layers ONE accent on the calico base. Core default = ginger; RoastMyRide = ember.","name":"Accent ramp (per-app)"},{"path":"guidelines/color-brand.card.html","group":"Colors","viewport":"700x170","subtitle":"The shared brand neutrals: cream + ginger + charcoal (constant across apps)","name":"Calico base — Callie's coat"},{"path":"guidelines/color-foundation.card.html","group":"Colors","viewport":"700x150","subtitle":"Bright warm base, never dark mode. ink 16.8:1 on canvas ✓","name":"Foundation — canvas, surfaces & ink"},{"path":"guidelines/color-semantic.card.html","group":"Colors","viewport":"700x160","subtitle":"Every functional pairing passes WCAG AA","name":"Semantic + AA-checked pairings"},{"path":"guidelines/color-sticker.card.html","group":"Colors","viewport":"700x150","subtitle":"DECORATION LAYER ONLY — never carries text contrast","name":"Sticker-set + clash accents"},{"path":"components/cast/cast.card.html","group":"Components","viewport":"700x420","subtitle":"The named voice cast who deliver the roast (Callie only reacts)","name":"The Cast — 8 roaster avatars"},{"path":"components/core/core.card.html","group":"Components","viewport":"700x460","subtitle":"Glossy inflatable primitives with squish press","name":"Core — Buttons, Chips, Inputs, Badges"},{"path":"components/feedback/feedback.card.html","group":"Components","viewport":"700x420","subtitle":"Bouncy sheet, status toasts, decoration-only confetti","name":"Feedback — Sheet, Toast, Confetti"},{"path":"components/mascot/mascot-library.card.html","group":"Components","viewport":"700x360","subtitle":"The calico face of Callie's Universe; one character, nine states","name":"Callie — the 9-state mascot"},{"path":"components/mascot/mascot.card.html","group":"Components","viewport":"700x360","subtitle":"Idle-cycling, context-aware Callie with Clippy-style tips","name":"Callie host — the live brain"},{"path":"components/share/share.card.html","group":"RoastMyRide (app-layer)","viewport":"700x520","subtitle":"App-specific (NOT core): the roast share frame + credit bundles","name":"Share — ShareCard & Credit tiles"},{"path":"guidelines/elevation.card.html","group":"Spacing","viewport":"700x190","subtitle":"Warm-tinted shadow ramp + the inflatable gloss","name":"Elevation — glossy, not flat"},{"path":"guidelines/radius-scale.card.html","group":"Spacing","viewport":"700x170","subtitle":"Inflatable language: generous rounding, pill controls","name":"Radius — chunky & squishy"},{"path":"guidelines/spacing-scale.card.html","group":"Spacing","viewport":"700x150","subtitle":"Generous, chunky rhythm","name":"Spacing scale — 4px base"},{"path":"guidelines/type-companion.card.html","group":"Type","viewport":"700x250","subtitle":"The quiet, highly-legible sans carries all small functional text.","name":"Companion scale — Hanken Grotesque"},{"path":"guidelines/type-display.card.html","group":"Type","viewport":"700x300","subtitle":"Chunky, confident, oversized up top. Never below ~18px.","name":"Display scale — Baloo 2"},{"path":"guidelines/type-pairing.card.html","group":"Type","viewport":"700x230","subtitle":"Dramatic contrast: loud display headline, quiet body beneath.","name":"Pairing in use — display + companion"},{"path":"apps/roastmyride-web/index.html","group":"Website","viewport":"1280x900","subtitle":"One loud viral page, single CTA: install","name":"RoastMyRide landing page"}],"templates":[],"hasThumbnailHtml":false,"globalCssPaths":["core/tokens/fonts.css","core/tokens/palette.css","core/tokens/colors.css","core/tokens/typography.css","core/tokens/spacing.css","core/tokens/radius.css","core/tokens/elevation.css","core/tokens/motion.css","styles.css"],"tokens":[{"name":"--cream","value":"#FFF6EC","kind":"color","definedIn":"core/tokens/palette.css"},{"name":"--cream-50","value":"#FFFDF9","kind":"color","definedIn":"core/tokens/palette.css"},{"name":"--cream-200","value":"#FBEEDF","kind":"color","definedIn":"core/tokens/palette.css"},{"name":"--ginger-700","value":"#8F4214","kind":"color","definedIn":"core/tokens/palette.css","annotation":"color"},{"name":"--ginger-600","value":"#B4561C","kind":"color","definedIn":"core/tokens/palette.css","annotation":"color"},{"name":"--ginger-500","value":"#D9772E","kind":"color","definedIn":"core/tokens/palette.css","annotation":"color"},{"name":"--ginger-400","value":"#E88B3D","kind":"color","definedIn":"core/tokens/palette.css","annotation":"color"},{"name":"--ginger-300","value":"#F2A864","kind":"color","definedIn":"core/tokens/palette.css","annotation":"color"},{"name":"--ginger-200","value":"#F8C794","kind":"color","definedIn":"core/tokens/palette.css","annotation":"color"},{"name":"--charcoal-900","value":"#2A2420","kind":"color","definedIn":"core/tokens/palette.css","annotation":"color"},{"name":"--charcoal-700","value":"#4A413A","kind":"color","definedIn":"core/tokens/palette.css","annotation":"color"},{"name":"--charcoal-600","value":"#5C5149","kind":"color","definedIn":"core/tokens/palette.css","annotation":"color"},{"name":"--charcoal-500","value":"#6E635A","kind":"color","definedIn":"core/tokens/palette.css","annotation":"color"},{"name":"--accent-700","value":"var(--ginger-700)","kind":"color","definedIn":"core/tokens/palette.css"},{"name":"--accent-600","value":"var(--ginger-600)","kind":"color","definedIn":"core/tokens/palette.css"},{"name":"--accent-500","value":"var(--ginger-500)","kind":"color","definedIn":"core/tokens/palette.css"},{"name":"--accent-bright","value":"var(--ginger-400)","kind":"color","definedIn":"core/tokens/palette.css"},{"name":"--accent-bright-2","value":"var(--ginger-300)","kind":"color","definedIn":"core/tokens/palette.css"},{"name":"--accent-warm","value":"var(--ginger-300)","kind":"color","definedIn":"core/tokens/palette.css"},{"name":"--accent-warm-2","value":"var(--ginger-200)","kind":"color","definedIn":"core/tokens/palette.css"},{"name":"--accent-soft","value":"#FFF1DE","kind":"color","definedIn":"core/tokens/palette.css"},{"name":"--ember-700","value":"var(--accent-700)","kind":"color","definedIn":"core/tokens/colors.css","annotation":"color"},{"name":"--ember-600","value":"var(--accent-600)","kind":"color","definedIn":"core/tokens/colors.css","annotation":"color"},{"name":"--ember-500","value":"var(--accent-500)","kind":"color","definedIn":"core/tokens/colors.css","annotation":"color"},{"name":"--flame-500","value":"var(--accent-bright)","kind":"color","definedIn":"core/tokens/colors.css","annotation":"color"},{"name":"--flame-400","value":"var(--accent-bright-2)","kind":"color","definedIn":"core/tokens/colors.css","annotation":"color"},{"name":"--heat-400","value":"var(--accent-warm)","kind":"color","definedIn":"core/tokens/colors.css","annotation":"color"},{"name":"--heat-300","value":"var(--accent-warm-2)","kind":"color","definedIn":"core/tokens/colors.css","annotation":"color"},{"name":"--pop-cyan","value":"#07B6CE","kind":"color","definedIn":"core/tokens/colors.css","annotation":"color"},{"name":"--pop-pink","value":"#FF2E9A","kind":"color","definedIn":"core/tokens/colors.css","annotation":"color"},{"name":"--canvas","value":"var(--cream)","kind":"color","definedIn":"core/tokens/colors.css"},{"name":"--canvas-sink","value":"var(--cream-200)","kind":"color","definedIn":"core/tokens/colors.css"},{"name":"--surface","value":"#FFFFFF","kind":"color","definedIn":"core/tokens/colors.css"},{"name":"--ink","value":"var(--charcoal-900)","kind":"color","definedIn":"core/tokens/colors.css"},{"name":"--ink-soft","value":"#5C4631","kind":"color","definedIn":"core/tokens/colors.css","annotation":"color"},{"name":"--ink-faint","value":"#8A7256","kind":"color","definedIn":"core/tokens/colors.css","annotation":"color"},{"name":"--on-ember","value":"#FFFFFF","kind":"color","definedIn":"core/tokens/colors.css"},{"name":"--hairline","value":"#EAD9C9","kind":"color","definedIn":"core/tokens/colors.css","annotation":"color"},{"name":"--focus-ring","value":"#07B6CE","kind":"color","definedIn":"core/tokens/colors.css","annotation":"color"},{"name":"--sticker-yellow","value":"#FFCB2B","kind":"color","definedIn":"core/tokens/colors.css","annotation":"color"},{"name":"--sticker-lime","value":"#8BE04E","kind":"color","definedIn":"core/tokens/colors.css","annotation":"color"},{"name":"--sticker-cyan","value":"#2BD4E8","kind":"color","definedIn":"core/tokens/colors.css","annotation":"color"},{"name":"--sticker-pink","value":"#FF4FA3","kind":"color","definedIn":"core/tokens/colors.css","annotation":"color"},{"name":"--sticker-purple","value":"#8B5CF6","kind":"color","definedIn":"core/tokens/colors.css","annotation":"color"},{"name":"--sticker-sky","value":"#3B9DFF","kind":"color","definedIn":"core/tokens/colors.css","annotation":"color"},{"name":"--success","value":"#1E8E4E","kind":"color","definedIn":"core/tokens/colors.css","annotation":"color"},{"name":"--warning","value":"#B8730A","kind":"color","definedIn":"core/tokens/colors.css","annotation":"color"},{"name":"--danger","value":"#C7340F","kind":"color","definedIn":"core/tokens/colors.css","annotation":"color"},{"name":"--info","value":"#0A6E9E","kind":"color","definedIn":"core/tokens/colors.css","annotation":"color"},{"name":"--bg-page","value":"var(--canvas)","kind":"color","definedIn":"core/tokens/colors.css"},{"name":"--bg-sunken","value":"var(--canvas-sink)","kind":"color","definedIn":"core/tokens/colors.css"},{"name":"--surface-card","value":"var(--surface)","kind":"color","definedIn":"core/tokens/colors.css"},{"name":"--text-strong","value":"var(--ink)","kind":"font","definedIn":"core/tokens/colors.css"},{"name":"--text-body","value":"var(--ink)","kind":"font","definedIn":"core/tokens/colors.css"},{"name":"--text-muted","value":"var(--ink-soft)","kind":"font","definedIn":"core/tokens/colors.css"},{"name":"--text-hint","value":"var(--ink-faint)","kind":"font","definedIn":"core/tokens/colors.css"},{"name":"--action-primary","value":"var(--accent-600)","kind":"color","definedIn":"core/tokens/colors.css"},{"name":"--action-primary-hover","value":"var(--accent-500)","kind":"color","definedIn":"core/tokens/colors.css"},{"name":"--action-primary-pressed","value":"var(--accent-700)","kind":"color","definedIn":"core/tokens/colors.css"},{"name":"--action-accent","value":"var(--accent-bright)","kind":"color","definedIn":"core/tokens/colors.css"},{"name":"--border-subtle","value":"var(--hairline)","kind":"color","definedIn":"core/tokens/colors.css"},{"name":"--on-accent","value":"var(--on-ember)","kind":"color","definedIn":"core/tokens/colors.css"},{"name":"--font-display","value":"\"Baloo 2\", \"Trebuchet MS\", system-ui, sans-serif","kind":"font","definedIn":"core/tokens/typography.css"},{"name":"--font-body","value":"\"Hanken Grotesque\", system-ui, -apple-system, sans-serif","kind":"font","definedIn":"core/tokens/typography.css"},{"name":"--fw-body","value":"400","kind":"font","definedIn":"core/tokens/typography.css","annotation":"font"},{"name":"--fw-medium","value":"500","kind":"font","definedIn":"core/tokens/typography.css","annotation":"font"},{"name":"--fw-semibold","value":"600","kind":"font","definedIn":"core/tokens/typography.css","annotation":"font"},{"name":"--fw-bold","value":"700","kind":"font","definedIn":"core/tokens/typography.css","annotation":"font"},{"name":"--fw-display","value":"700","kind":"font","definedIn":"core/tokens/typography.css","annotation":"font"},{"name":"--fw-heavy","value":"800","kind":"font","definedIn":"core/tokens/typography.css","annotation":"font"},{"name":"--fs-reveal","value":"72px","kind":"spacing","definedIn":"core/tokens/typography.css"},{"name":"--fs-d1","value":"52px","kind":"spacing","definedIn":"core/tokens/typography.css"},{"name":"--fs-d2","value":"40px","kind":"spacing","definedIn":"core/tokens/typography.css"},{"name":"--fs-d3","value":"30px","kind":"spacing","definedIn":"core/tokens/typography.css"},{"name":"--fs-d4","value":"22px","kind":"spacing","definedIn":"core/tokens/typography.css"},{"name":"--fs-lead","value":"18px","kind":"spacing","definedIn":"core/tokens/typography.css"},{"name":"--fs-body","value":"16px","kind":"spacing","definedIn":"core/tokens/typography.css"},{"name":"--fs-sm","value":"14px","kind":"spacing","definedIn":"core/tokens/typography.css"},{"name":"--fs-cap","value":"13px","kind":"spacing","definedIn":"core/tokens/typography.css"},{"name":"--fs-legal","value":"12px","kind":"spacing","definedIn":"core/tokens/typography.css"},{"name":"--lh-tight","value":"0.98","kind":"font","definedIn":"core/tokens/typography.css","annotation":"font"},{"name":"--lh-snug","value":"1.08","kind":"font","definedIn":"core/tokens/typography.css","annotation":"font"},{"name":"--lh-head","value":"1.15","kind":"font","definedIn":"core/tokens/typography.css","annotation":"font"},{"name":"--lh-body","value":"1.5","kind":"font","definedIn":"core/tokens/typography.css","annotation":"font"},{"name":"--lh-relaxed","value":"1.6","kind":"font","definedIn":"core/tokens/typography.css","annotation":"font"},{"name":"--ls-tight","value":"-0.02em","kind":"font","definedIn":"core/tokens/typography.css","annotation":"font"},{"name":"--ls-normal","value":"0","kind":"font","definedIn":"core/tokens/typography.css","annotation":"font"},{"name":"--ls-wide","value":"0.04em","kind":"font","definedIn":"core/tokens/typography.css","annotation":"font"},{"name":"--type-reveal","value":"var(--fw-heavy) var(--fs-reveal)/var(--lh-tight) var(--font-display)","kind":"font","definedIn":"core/tokens/typography.css"},{"name":"--type-d1","value":"var(--fw-heavy) var(--fs-d1)/var(--lh-tight) var(--font-display)","kind":"font","definedIn":"core/tokens/typography.css"},{"name":"--type-d2","value":"var(--fw-heavy) var(--fs-d2)/var(--lh-snug) var(--font-display)","kind":"font","definedIn":"core/tokens/typography.css"},{"name":"--type-d3","value":"var(--fw-display) var(--fs-d3)/var(--lh-head) var(--font-display)","kind":"font","definedIn":"core/tokens/typography.css"},{"name":"--type-d4","value":"var(--fw-display) var(--fs-d4)/var(--lh-head) var(--font-display)","kind":"font","definedIn":"core/tokens/typography.css"},{"name":"--type-button","value":"var(--fw-display) var(--fs-lead)/1 var(--font-display)","kind":"font","definedIn":"core/tokens/typography.css"},{"name":"--type-lead","value":"var(--fw-medium) var(--fs-lead)/var(--lh-body) var(--font-body)","kind":"font","definedIn":"core/tokens/typography.css"},{"name":"--type-body","value":"var(--fw-body) var(--fs-body)/var(--lh-body) var(--font-body)","kind":"font","definedIn":"core/tokens/typography.css"},{"name":"--type-sm","value":"var(--fw-medium) var(--fs-sm)/var(--lh-body) var(--font-body)","kind":"font","definedIn":"core/tokens/typography.css"},{"name":"--type-cap","value":"var(--fw-semibold) var(--fs-cap)/var(--lh-snug) var(--font-body)","kind":"font","definedIn":"core/tokens/typography.css"},{"name":"--type-legal","value":"var(--fw-body) var(--fs-legal)/var(--lh-body) var(--font-body)","kind":"font","definedIn":"core/tokens/typography.css"},{"name":"--space-0","value":"0","kind":"spacing","definedIn":"core/tokens/spacing.css"},{"name":"--space-1","value":"4px","kind":"spacing","definedIn":"core/tokens/spacing.css"},{"name":"--space-2","value":"8px","kind":"spacing","definedIn":"core/tokens/spacing.css"},{"name":"--space-3","value":"12px","kind":"spacing","definedIn":"core/tokens/spacing.css"},{"name":"--space-4","value":"16px","kind":"spacing","definedIn":"core/tokens/spacing.css"},{"name":"--space-5","value":"20px","kind":"spacing","definedIn":"core/tokens/spacing.css"},{"name":"--space-6","value":"24px","kind":"spacing","definedIn":"core/tokens/spacing.css"},{"name":"--space-7","value":"32px","kind":"spacing","definedIn":"core/tokens/spacing.css"},{"name":"--space-8","value":"40px","kind":"spacing","definedIn":"core/tokens/spacing.css"},{"name":"--space-9","value":"48px","kind":"spacing","definedIn":"core/tokens/spacing.css"},{"name":"--space-10","value":"64px","kind":"spacing","definedIn":"core/tokens/spacing.css"},{"name":"--space-11","value":"80px","kind":"spacing","definedIn":"core/tokens/spacing.css"},{"name":"--space-12","value":"104px","kind":"spacing","definedIn":"core/tokens/spacing.css"},{"name":"--gutter","value":"var(--space-5)","kind":"color","definedIn":"core/tokens/spacing.css"},{"name":"--stack-tight","value":"var(--space-2)","kind":"color","definedIn":"core/tokens/spacing.css"},{"name":"--stack","value":"var(--space-4)","kind":"color","definedIn":"core/tokens/spacing.css"},{"name":"--stack-loose","value":"var(--space-7)","kind":"color","definedIn":"core/tokens/spacing.css"},{"name":"--section-gap","value":"var(--space-10)","kind":"spacing","definedIn":"core/tokens/spacing.css"},{"name":"--tap-min","value":"48px","kind":"spacing","definedIn":"core/tokens/spacing.css"},{"name":"--tap-cozy","value":"56px","kind":"spacing","definedIn":"core/tokens/spacing.css"},{"name":"--tap-hero","value":"64px","kind":"spacing","definedIn":"core/tokens/spacing.css"},{"name":"--app-max","value":"430px","kind":"spacing","definedIn":"core/tokens/spacing.css"},{"name":"--content-max","value":"1120px","kind":"spacing","definedIn":"core/tokens/spacing.css"},{"name":"--radius-xs","value":"8px","kind":"radius","definedIn":"core/tokens/radius.css"},{"name":"--radius-sm","value":"12px","kind":"radius","definedIn":"core/tokens/radius.css"},{"name":"--radius-md","value":"18px","kind":"radius","definedIn":"core/tokens/radius.css"},{"name":"--radius-lg","value":"26px","kind":"radius","definedIn":"core/tokens/radius.css"},{"name":"--radius-xl","value":"34px","kind":"radius","definedIn":"core/tokens/radius.css"},{"name":"--radius-2xl","value":"44px","kind":"radius","definedIn":"core/tokens/radius.css"},{"name":"--radius-pill","value":"999px","kind":"radius","definedIn":"core/tokens/radius.css"},{"name":"--radius-blob","value":"48% 52% 56% 44% / 52% 46% 54% 48%","kind":"radius","definedIn":"core/tokens/radius.css"},{"name":"--radius-button","value":"var(--radius-pill)","kind":"radius","definedIn":"core/tokens/radius.css"},{"name":"--radius-chip","value":"var(--radius-pill)","kind":"radius","definedIn":"core/tokens/radius.css"},{"name":"--radius-card","value":"var(--radius-lg)","kind":"radius","definedIn":"core/tokens/radius.css"},{"name":"--radius-input","value":"var(--radius-md)","kind":"radius","definedIn":"core/tokens/radius.css"},{"name":"--radius-sheet","value":"var(--radius-xl)","kind":"radius","definedIn":"core/tokens/radius.css"},{"name":"--elev-1","value":"0 2px 6px rgba(120, 52, 12, 0.10)","kind":"shadow","definedIn":"core/tokens/elevation.css"},{"name":"--elev-2","value":"0 6px 16px rgba(120, 52, 12, 0.14)","kind":"shadow","definedIn":"core/tokens/elevation.css"},{"name":"--elev-3","value":"0 12px 28px rgba(120, 52, 12, 0.18)","kind":"shadow","definedIn":"core/tokens/elevation.css"},{"name":"--elev-4","value":"0 22px 48px rgba(120, 52, 12, 0.22)","kind":"shadow","definedIn":"core/tokens/elevation.css"},{"name":"--gloss-card","value":"inset 0 2px 0 rgba(255, 255, 255, 0.85),\n    inset 0 -6px 14px rgba(120, 52, 12, 0.06),\n    0 10px 24px rgba(120, 52, 12, 0.16)","kind":"shadow","definedIn":"core/tokens/elevation.css","annotation":"shadow"},{"name":"--gloss-primary","value":"inset 0 2px 0 rgba(255, 255, 255, 0.45),\n    inset 0 -8px 16px rgba(120, 30, 0, 0.30),\n    0 10px 22px rgba(199, 52, 15, 0.40)","kind":"shadow","definedIn":"core/tokens/elevation.css","annotation":"shadow"},{"name":"--gloss-primary-pressed","value":"inset 0 3px 10px rgba(120, 30, 0, 0.45),\n    0 3px 8px rgba(199, 52, 15, 0.30)","kind":"shadow","definedIn":"core/tokens/elevation.css","annotation":"shadow"},{"name":"--gloss-chip","value":"inset 0 1px 0 rgba(255, 255, 255, 0.7),\n    0 3px 8px rgba(120, 52, 12, 0.14)","kind":"shadow","definedIn":"core/tokens/elevation.css","annotation":"shadow"},{"name":"--shadow-sticker","value":"0 2px 0 rgba(34, 20, 3, 0.18), 0 6px 12px rgba(34, 20, 3, 0.12)","kind":"shadow","definedIn":"core/tokens/elevation.css"},{"name":"--ring","value":"0 0 0 3px var(--canvas), 0 0 0 6px var(--focus-ring)","kind":"color","definedIn":"core/tokens/elevation.css"},{"name":"--elevation-card","value":"var(--gloss-card)","kind":"shadow","definedIn":"core/tokens/elevation.css"},{"name":"--elevation-cta","value":"var(--gloss-primary)","kind":"shadow","definedIn":"core/tokens/elevation.css"},{"name":"--elevation-sheet","value":"var(--elev-4)","kind":"shadow","definedIn":"core/tokens/elevation.css"},{"name":"--dur-1","value":"90ms","kind":"other","definedIn":"core/tokens/motion.css","annotation":"other"},{"name":"--dur-2","value":"160ms","kind":"other","definedIn":"core/tokens/motion.css","annotation":"other"},{"name":"--dur-3","value":"260ms","kind":"other","definedIn":"core/tokens/motion.css","annotation":"other"},{"name":"--dur-4","value":"420ms","kind":"other","definedIn":"core/tokens/motion.css","annotation":"other"},{"name":"--dur-cook","value":"2600ms","kind":"other","definedIn":"core/tokens/motion.css","annotation":"other"},{"name":"--ease-out","value":"cubic-bezier(0.22, 1, 0.36, 1)","kind":"other","definedIn":"core/tokens/motion.css","annotation":"other"},{"name":"--ease-in","value":"cubic-bezier(0.55, 0, 0.7, 0.2)","kind":"other","definedIn":"core/tokens/motion.css","annotation":"other"},{"name":"--ease-spring","value":"cubic-bezier(0.34, 1.56, 0.64, 1)","kind":"other","definedIn":"core/tokens/motion.css","annotation":"other"},{"name":"--ease-bounce","value":"cubic-bezier(0.2, 1.4, 0.4, 1)","kind":"other","definedIn":"core/tokens/motion.css","annotation":"other"},{"name":"--press-scale","value":"0.99","kind":"other","definedIn":"core/tokens/motion.css","annotation":"other"},{"name":"--lift-scale","value":"1","kind":"other","definedIn":"core/tokens/motion.css","annotation":"other"},{"name":"--transition-press","value":"opacity var(--dur-1) linear","kind":"other","definedIn":"core/tokens/motion.css","annotation":"other"},{"name":"--transition-state","value":"all var(--dur-2) var(--ease-out)","kind":"other","definedIn":"core/tokens/motion.css","annotation":"other"},{"name":"--transition-enter","value":"opacity var(--dur-2) linear","kind":"other","definedIn":"core/tokens/motion.css","annotation":"other"}],"themes":[],"fonts":[],"brandFonts":[{"family":"Baloo 2","status":"ok","tokens":["--font-display"],"path":"core/tokens/typography.css"},{"family":"Hanken Grotesque","status":"ok","tokens":["--font-body"],"path":"core/tokens/typography.css"}],"source":"spa"}